{
  "eid": "69d47fd9b977fb2c47459f5b",
  "title": "4.7（上）多看少动",
  "audio_url": "https://media.xyzcdn.net/68b8197aad2ca29a39848ea3/Fk_habmeylyE6v-hfMQOXU_S866U.m4a",
  "pub_date": "2026-04-07T03:55:40.572Z",
  "duration": 175,
  "description": "",
  "analysis": {
    "summary": "本期内容主要讨论了节后首日市场的冲高回落表现，主播分享了自己在游戏板块和资源类标的上的操作逻辑。当前市场处于缩量磨底阶段，波动较为反复，建议投资者采取做T或持股不动的策略。主播目前保持五至六成仓位，正等待市场出现进一步加速下跌的机会以进行补仓。",
    "key_points": [
      "指数节后首日冲高回落符合预期，市场处于缩量磨底阶段。",
      "通过日内交易（做T）获得约1%的平均收益，强调了震荡市中波段操作的重要性。",
      "看好游戏板块，理由包括业绩稳健、利好消息支撑以及前期下跌幅度和时长已足够。",
      "承认在资源股（铜及锂电池相关）上存在卖早了的失误，但强调保住利润是前提。",
      "市场大跌概率不高，更多以阴跌或震荡形式寻找底部，过程会比较痛苦。",
      "目前的策略是控制在5-6成仓位，保留资金以备在市场加速下跌时加仓。",
      "警惕追涨杀跌的情绪化操作，尤其是在节前恐慌割肉、节后冲高追入的行为。"
    ],
    "investment_targets": [
      {
        "name": "游戏板块",
        "context": "由于业绩好、有利好消息且跌幅时间足够，主播在今日市场跳水过程中再次补仓。"
      },
      {
        "name": "大冶特钢/铜/锂电池相关标的",
        "context": "主播提到在节前最后一个交易日以为是高点而卖出，结果今日最高涨幅达15个点，感叹卖早了。"
      },
      {
        "name": "A股大盘指数",
        "context": "讨论了节后首日指数冲高回落的走势以及当前不到8000亿成交量的缩量现状。"
      }
    ],
    "risk_warnings": [
      "缩量磨底阶段的市场震荡和阴跌会给投资者带来心理痛苦。",
      "盲目追涨操作，容易在冲高时被套，随后在低开调整中再次割肉。",
      "过早满仓可能导致在未来出现真正加速下跌机会时缺乏加仓资金。"
    ],
    "market_outlook": "neutral",
    "target_audience": "具备一定交易经验、关注板块轮动及技术面操作的中短线个人投资者。"
  },
  "analyzed_at": "2026-04-07T04:07:58.851325+00:00"
}